{
    "index":{
        "title":"Home",
        "type":"page",
        "display":"hidden",
        "theme":{
            "layout":"raw"
        }
    },
    "infraops-design":{
        "title":"InfraOps",
        "type":"page",
        "display":"hidden",
        "theme":{
            "layout":"raw"
        }
    },
    "devops-design":{
        "title":"DevOps",
        "type":"page",
        "display":"hidden",
        "theme":{
            "layout":"raw"
        }
    },
    "distribution-design":{
        "title":"Distribution",
        "type":"page",
        "display":"hidden",
        "theme":{
            "layout":"raw"
        }
    },
    "help-and-support":{
        "title":"Help and Support",
        "type":"page",
        "display":"hidden",
        "theme":{
            "layout":"raw"
        }
    },
    "privacy-policy":{
        "title":"Privacy Policy",
        "type":"page",
        "display":"hidden",
        "theme":{
            "layout":"raw"
        }
    },
    "terms-of-services":{
        "title":"Terms of Services",
        "type":"page",
        "display":"hidden",
        "theme":{
            "layout":"raw"
        }
    },
    "devops":{
        "title":"DevOps",
        "type":"page"
    },
    "infraops":{
        "title":"InfraOps",
        "type":"page"
    },
    "distribution":{
        "title":"Distribution",
        "type":"page"
    }
}